{
  "$schemaVersion": "2.0",
  "template": "sales-one-pager",
  "slots": [
    {
      "id": "ctaBtn",
      "type": "text",
      "label": "Cta Btn",
      "maxLength": 90,
      "required": true
    },
    {
      "id": "ctaKicker",
      "type": "text",
      "label": "Cta Kicker",
      "maxLength": 90
    },
    {
      "id": "ctaPlace",
      "type": "text",
      "label": "Cta Place",
      "maxLength": 90
    },
    {
      "id": "heroKicker",
      "type": "text",
      "label": "Hero Kicker",
      "maxLength": 90
    },
    {
      "id": "processTitle",
      "type": "text",
      "label": "Process Title",
      "maxLength": 90
    },
    {
      "id": "stat1",
      "type": "text",
      "label": "Stat1",
      "maxLength": 90
    },
    {
      "id": "stat1l",
      "type": "text",
      "label": "Stat1L",
      "maxLength": 90
    },
    {
      "id": "stat2l",
      "type": "text",
      "label": "Stat2L",
      "maxLength": 90
    },
    {
      "id": "stat3l",
      "type": "text",
      "label": "Stat3L",
      "maxLength": 90
    },
    {
      "id": "stat4",
      "type": "text",
      "label": "Stat4",
      "maxLength": 90
    },
    {
      "id": "stat4l",
      "type": "text",
      "label": "Stat4L",
      "maxLength": 90
    }
  ]
}
